{
    "queued_space_list": {
        "1DXGyvaBpXdJM": {
            "created_at": "2023-04-27T14:59:19.000Z",
            "creator_id": "1639500966826213378",
            "host_ids": [
                "1639500966826213378"
            ],
            "id": "1DXGyvaBpXdJM",
            "participant_count": 0,
            "scheduled_start": "2023-05-04T00:00:00.000Z",
            "state": "scheduled",
            "title": "Coining Reason, 4: The World Brain"
        },
        "1YqKDoyOXpBxV": {
            "created_at": "2023-04-29T07:43:09.000Z",
            "creator_id": "1609876493794177025",
            "host_ids": [
                "1609876493794177025"
            ],
            "id": "1YqKDoyOXpBxV",
            "participant_count": 0,
            "scheduled_start": "2023-05-05T12:00:49.000Z",
            "state": "scheduled",
            "title": "RAC FM Special: Empawrium Beta Launch, Wheelchair Mafia and Finn's GM?"
        },
        "1BRKjZXDgYZKw": {
            "created_at": "2023-04-27T16:36:28.000Z",
            "creator_id": "1515104342906327045",
            "host_ids": [
                "1515104342906327045"
            ],
            "id": "1BRKjZXDgYZKw",
            "participant_count": 0,
            "scheduled_start": "2023-05-02T17:00:00.000Z",
            "state": "scheduled",
            "title": "Liquidity Alliance AMA W/ FlowTraders \ud83d\udea2"
        },
        "1ZkKzXkQMYWJv": {
            "created_at": "2023-04-28T17:32:00.000Z",
            "creator_id": "2267277648",
            "host_ids": [
                "2267277648"
            ],
            "id": "1ZkKzXkQMYWJv",
            "participant_count": 0,
            "scheduled_start": "2023-05-01T14:15:00.000Z",
            "state": "scheduled",
            "title": "Q&A with Leap wallet - #IBC GANG"
        },
        "1MnGnpNOAPExO": {
            "created_at": "2023-04-28T18:46:19.000Z",
            "creator_id": "1062118922147659776",
            "host_ids": [
                "1062118922147659776"
            ],
            "id": "1MnGnpNOAPExO",
            "participant_count": 0,
            "scheduled_start": "2023-05-02T14:00:00.000Z",
            "state": "scheduled",
            "title": "Injective Hackathon Panel: Tendermint and Shared Security "
        },
        "1rmGPkQdXDLKN": {
            "created_at": "2023-04-27T14:56:57.000Z",
            "creator_id": "1504064670566699008",
            "host_ids": [
                "1504064670566699008"
            ],
            "id": "1rmGPkQdXDLKN",
            "participant_count": 0,
            "scheduled_start": "2023-05-04T00:00:00.000Z",
            "state": "scheduled",
            "title": "Coining Reason, 4: The World Brain"
        },
        "1zqKVPOoAyPJB": {
            "created_at": "2023-04-28T21:53:09.000Z",
            "creator_id": "1153962373683675136",
            "host_ids": [
                "1153962373683675136"
            ],
            "id": "1zqKVPOoAyPJB",
            "participant_count": 0,
            "scheduled_start": "2023-04-29T21:00:00.000Z",
            "state": "scheduled",
            "title": "#bye Imposter projects & team member scams. Cheqd is #InTheSpotlight"
        },
        "1dRJZMgEPAzGB": {
            "created_at": "2023-04-24T14:53:43.000Z",
            "creator_id": "1357133940109103104",
            "host_ids": [
                "1357133940109103104"
            ],
            "id": "1dRJZMgEPAzGB",
            "participant_count": 0,
            "scheduled_start": "2023-05-03T16:00:00.000Z",
            "state": "scheduled",
            "title": "Updates from the Lab - Axelar and Autonomy Network \ud83e\udd16"
        },
        "1rmGPkQLgmmKN": {
            "created_at": "2023-04-26T07:12:32.000Z",
            "creator_id": "1500172416084938755",
            "host_ids": [
                "1500172416084938755"
            ],
            "id": "1rmGPkQLgmmKN",
            "participant_count": 0,
            "scheduled_start": "2023-05-11T16:00:00.000Z",
            "state": "scheduled",
            "title": "#YieldmosWeekly - Community Call + Cosmonauts \ud83d\udc9c\u269b\ufe0f"
        },
        "1lPJqBdEmnExb": {
            "created_at": "2023-04-26T07:12:15.000Z",
            "creator_id": "1500172416084938755",
            "host_ids": [
                "1500172416084938755"
            ],
            "id": "1lPJqBdEmnExb",
            "participant_count": 0,
            "scheduled_start": "2023-05-04T16:00:00.000Z",
            "state": "scheduled",
            "title": "#YieldmosWeekly - Community Call + Cosmonauts \ud83d\udc9c\u269b\ufe0f"
        },
        "1OwxWwOazopxQ": {
            "created_at": "2023-04-26T07:11:06.000Z",
            "creator_id": "1500172416084938755",
            "host_ids": [
                "1500172416084938755"
            ],
            "id": "1OwxWwOazopxQ",
            "participant_count": 0,
            "scheduled_start": "2023-05-18T16:00:00.000Z",
            "state": "scheduled",
            "title": "#YieldmosWeekly - Community Call + Cosmonauts \ud83d\udc9c\u269b\ufe0f"
        },
        "1ypKddOookNKW": {
            "created_at": "2023-04-30T14:17:41.000Z",
            "creator_id": "1609876493794177025",
            "host_ids": [
                "1609876493794177025"
            ],
            "id": "1ypKddOookNKW",
            "participant_count": 0,
            "scheduled_start": "2023-04-30T14:20:28.000Z",
            "state": "scheduled",
            "title": "\ud83e\udd9dRAC FM: Celebrating TerraSpaces prop passing\ud83c\udf89\ud83c\udf8a\ud83c\udf7e\ud83e\udd42\ud83e\udd1d"
        }
    }
}